dispruce/__init__.py
dispruce/libspruce.so
dispruce/sprucepy.cpython-312-x86_64-linux-gnu.so
spruce_package-2.0.0.dist-info/LICENSE
spruce_package-2.0.0.dist-info/METADATA
spruce_package-2.0.0.dist-info/WHEEL
spruce_package-2.0.0.dist-info/RECORD
