Metadata-Version: 2.1
Name: spruce-package
Version: 2.0.0
Summary: AI-powered resource optimization and efficiency analysis library for retail banks
License: Proprietary
Author: deinnovatie SAS
Author-email: support@deinnovatie.com
Requires-Python: ==3.12.3
Classifier: License :: Other/Proprietary License
Classifier: Programming Language :: Python :: 3
Requires-Dist: pyarrow (==17.0.0)
